diffusechain/__init__.py
diffusechain/Automatic1111.py
diffusechain/chains/__init__.py
diffusechain/chains/consistentFaceChain.py
diffusechain/Diffusers.py
diffusechain-0.1.52.dist-info/LICENSE
diffusechain-0.1.52.dist-info/METADATA
diffusechain-0.1.52.dist-info/WHEEL
diffusechain-0.1.52.dist-info/RECORD
