Metadata-Version: 2.1
Name: diffusechain
Version: 0.1.52
Summary: 
Author: Adithya S K
Author-email: adithyaskolavi@gmail.com
Requires-Python: >=3.7,<4.0
Classifier: Programming Language :: Python :: 3
Classifier: Programming Language :: Python :: 3.7
Classifier: Programming Language :: Python :: 3.8
Classifier: Programming Language :: Python :: 3.9
Classifier: Programming Language :: Python :: 3.10
Classifier: Programming Language :: Python :: 3.11
Requires-Dist: aiohttp (>=3.8.4,<4.0.0)
Requires-Dist: pillow (>=10.0.0,<11.0.0)
Requires-Dist: requests (>=2.31.0,<3.0.0)
